twisted_s3/__init__.py
twisted_s3/auth.py
twisted_s3/client.py
twisted_s3/future.py
twisted_s3/response.py
twisted_s3-0.2.2.dist-info/DESCRIPTION.rst
twisted_s3-0.2.2.dist-info/METADATA
twisted_s3-0.2.2.dist-info/RECORD
twisted_s3-0.2.2.dist-info/WHEEL
twisted_s3-0.2.2.dist-info/metadata.json
twisted_s3-0.2.2.dist-info/top_level.txt
